LICENSE
MANIFEST.in
README.md
README.rst
setup.cfg
setup.py
docs/README.md
drf_url_filters.egg-info/PKG-INFO
drf_url_filters.egg-info/SOURCES.txt
drf_url_filters.egg-info/dependency_links.txt
drf_url_filters.egg-info/requires.txt
drf_url_filters.egg-info/top_level.txt
filters/__init__.py
filters/decorators.py
filters/metaclasses.py
filters/mixins.py
filters/schema.py
filters/validations.py