Metadata-Version: 1.1
Name: drf-url-filters
Version: 0.5.1
Summary: A django app to apply filters on drf querysets using query params with validations using voluptuous.
Home-page: https://github.com/manjitkumar/drf-url-filters
Author: Manjit Kumar
Author-email: manjit1727@gmail.com
License: UNKNOWN
Download-URL: https://github.com/manjitkumar/drf-url-filters/archive/v0.1.3.tar.gz
Keywords: drf-url-filters,filters,queryparameters
Platform: UNKNOWN
Classifier: Development Status :: 3 - Alpha
Classifier: Intended Audience :: Developers
Classifier: License :: OSI Approved :: MIT License
Classifier: Programming Language :: Python :: 2.7
